alphabetize_codeowners.py
alphabetize_codeowners-0.0.1.dist-info/entry_points.txt
alphabetize_codeowners-0.0.1.dist-info/LICENSE
alphabetize_codeowners-0.0.1.dist-info/WHEEL
alphabetize_codeowners-0.0.1.dist-info/METADATA
alphabetize_codeowners-0.0.1.dist-info/RECORD
